easy_sgr/__init__.py
easy_sgr/core/__init__.py
easy_sgr/core/agents.py
easy_sgr/core/llms.py
easy_sgr/core/tools.py
easy_sgr/sgr_agent_core/__init__.py
easy_sgr/sgr_agent_core/agent_config.py
easy_sgr/sgr_agent_core/agent_definition.py
easy_sgr/sgr_agent_core/agent_factory.py
easy_sgr/sgr_agent_core/base_agent.py
easy_sgr/sgr_agent_core/base_tool.py
easy_sgr/sgr_agent_core/models.py
easy_sgr/sgr_agent_core/next_step_tool.py
easy_sgr/sgr_agent_core/stream.py
easy_sgr/sgr_agent_core/agents/__init__.py
easy_sgr/sgr_agent_core/agents/sgr_agent.py
easy_sgr/sgr_agent_core/agents/sgr_tool_calling_agent.py
easy_sgr/sgr_agent_core/agents/tool_calling_agent.py
easy_sgr/sgr_agent_core/prompts/__init__.py
easy_sgr/sgr_agent_core/prompts/clarification_response.txt
easy_sgr/sgr_agent_core/prompts/initial_user_request.txt
easy_sgr/sgr_agent_core/prompts/research_system_prompt.txt
easy_sgr/sgr_agent_core/prompts/system_prompt.txt
easy_sgr/sgr_agent_core/server/__init__.py
easy_sgr/sgr_agent_core/server/__main__.py
easy_sgr/sgr_agent_core/server/app.py
easy_sgr/sgr_agent_core/server/endpoints.py
easy_sgr/sgr_agent_core/server/models.py
easy_sgr/sgr_agent_core/server/settings.py
easy_sgr/sgr_agent_core/services/__init__.py
easy_sgr/sgr_agent_core/services/mcp_service.py
easy_sgr/sgr_agent_core/services/prompt_loader.py
easy_sgr/sgr_agent_core/services/registry.py
easy_sgr/sgr_agent_core/services/tavily_search.py
easy_sgr/sgr_agent_core/tools/__init__.py
easy_sgr/sgr_agent_core/tools/adapt_plan_tool.py
easy_sgr/sgr_agent_core/tools/clarification_tool.py
easy_sgr/sgr_agent_core/tools/create_report_tool.py
easy_sgr/sgr_agent_core/tools/extract_page_content_tool.py
easy_sgr/sgr_agent_core/tools/final_answer_tool.py
easy_sgr/sgr_agent_core/tools/generate_plan_tool.py
easy_sgr/sgr_agent_core/tools/reasoning_tool.py
easy_sgr/sgr_agent_core/tools/web_search_tool.py
easy_sgr-0.1.0.dist-info/licenses/LICENSE
easy_sgr-0.1.0.dist-info/METADATA
easy_sgr-0.1.0.dist-info/WHEEL
easy_sgr-0.1.0.dist-info/top_level.txt
easy_sgr-0.1.0.dist-info/RECORD
