Metadata-Version: 2.4
Name: easy-sgr
Version: 0.1.0
Summary: A simplified interface for SGR (Schema-Guided Reasoning) agents in LangChain style
Home-page: 
Author: Maksim
Author-email: Maksim <maks6863@gmail.com>
License: MIT
Keywords: sgr,schema-guided-reasoning,langchain,ai,llm,agent,openai,tool-calling
Classifier: Development Status :: 4 - Beta
Classifier: Intended Audience :: Developers
Classifier: License :: OSI Approved :: MIT License
Classifier: Programming Language :: Python :: 3
Classifier: Programming Language :: Python :: 3.10
Classifier: Programming Language :: Python :: 3.11
Classifier: Programming Language :: Python :: 3.12
Classifier: Topic :: Software Development :: Libraries :: Python Modules
Classifier: Topic :: Scientific/Engineering :: Artificial Intelligence
Requires-Python: >=3.10
License-File: LICENSE
Requires-Dist: fastmcp
Requires-Dist: jambo
Requires-Dist: openai
Requires-Dist: pydantic>=2.0
Requires-Dist: pydantic-settings
Requires-Dist: fastapi
Requires-Dist: uvicorn
Requires-Dist: pyyaml
Requires-Dist: httpx
Requires-Dist: tavily-python
Requires-Dist: python-dotenv
Provides-Extra: dev
Requires-Dist: pytest>=7.0; extra == "dev"
Requires-Dist: pytest-asyncio>=0.21; extra == "dev"
Dynamic: author
Dynamic: license-file
Dynamic: requires-python
